khbr/.DS_Store
khbr/__init__.py
khbr/_config.py
khbr/bossrush.py
khbr/enemies.yaml
khbr/enmpmanager.py
khbr/full_enemy_records.json
khbr/full_enemy_records_pc.json
khbr/integration_tests.py
khbr/integration_tests_long.py
khbr/location-ard-map.json
khbr/locations.yaml
khbr/longtests.py
khbr/msns.json
khbr/randomizer.py
khbr/randutils.py
khbr/test_aimanager.py
khbr/test_areadataprogram.py
khbr/test_assetgenerator.py
khbr/test_commandmanager.py
khbr/test_cutsceneremover.py
khbr/test_enemymanager.py
khbr/test_enemyseed.py
khbr/test_enmpmanager.py
khbr/test_locationmanager.py
khbr/test_memtmanager.py
khbr/test_mission.py
khbr/test_modwriter.py
khbr/test_randutils.py
khbr/test_spawnmanager.py
khbr/tests.py
khbr/testutils.py
khbr/textutils.py
khbr/utils.py
khbr/KH2/AiManager.py
khbr/KH2/AreaDataProgram.py
khbr/KH2/AreaDataScript.py
khbr/KH2/AssetGenerator.py
khbr/KH2/CommandManager.py
khbr/KH2/CutsceneRemover.py
khbr/KH2/EnemyManager.py
khbr/KH2/EnmpManager.py
khbr/KH2/KingdomHearts2.py
khbr/KH2/LocationManager.py
khbr/KH2/LuaManager.py
khbr/KH2/MemtManager.py
khbr/KH2/Mission.py
khbr/KH2/MissionManager.py
khbr/KH2/ModWriter.py
khbr/KH2/SpawnManager.py
khbr/KH2/__init__.py
khbr/KH2/__pycache__/AiManager.cpython-37.pyc
khbr/KH2/__pycache__/AreaDataScript.cpython-37.pyc
khbr/KH2/__pycache__/AssetGenerator.cpython-37.pyc
khbr/KH2/__pycache__/EnemyManager.cpython-37.pyc
khbr/KH2/__pycache__/EnmpManager.cpython-37.pyc
khbr/KH2/__pycache__/KingdomHearts2.cpython-37.pyc
khbr/KH2/__pycache__/LocationManager.cpython-37.pyc
khbr/KH2/__pycache__/Mission.cpython-37.pyc
khbr/KH2/__pycache__/MissionManager.cpython-37.pyc
khbr/KH2/__pycache__/ModWriter.cpython-37.pyc
khbr/KH2/__pycache__/SpawnManager.cpython-37.pyc
khbr/KH2/__pycache__/__init__.cpython-37.pyc
khbr/KH2/data/bonsVanilla.yml
khbr/KH2/data/bossrush.lua
khbr/KH2/data/cmdVanilla.yml
khbr/KH2/data/enemies.yaml
khbr/KH2/data/enmpVanilla.yml
khbr/KH2/data/fmlvVanilla.yml
khbr/KH2/data/full_enemy_records.json
khbr-4.0.5.dist-info/LICENSE
khbr-4.0.5.dist-info/METADATA
khbr-4.0.5.dist-info/WHEEL
khbr-4.0.5.dist-info/top_level.txt
khbr-4.0.5.dist-info/RECORD
