Metadata-Version: 2.1
Name: khbr
Version: 4.0.5
Home-page: https://github.com/thundrio-kh/khbr
Author: Thundrio
Author-email: thundrio@yahoo.com
Maintainer-email: thundrio@yahoo.com
License: MIT
Platform: any
Classifier: Intended Audience :: Developers
Classifier: Operating System :: OS Independent
Classifier: Programming Language :: Python :: 3
License-File: LICENSE
Requires-Dist: PyYAML
